README.md
setup.py
lylogger/__init__.py
lylogger.egg-info/PKG-INFO
lylogger.egg-info/SOURCES.txt
lylogger.egg-info/dependency_links.txt
lylogger.egg-info/top_level.txt