Metadata-Version: 1.1
Name: lylogger
Version: 0.1.1
Summary: This is a easy logger.
Home-page: https://github.com/GraySilver/Lylogger
Author: GraySilver
Author-email: allenyzx@163.com
License: MIT
Platform: UNKNOWN
Classifier: Environment :: Web Environment
Classifier: Intended Audience :: Developers
Classifier: Operating System :: OS Independent
Classifier: Topic :: Text Processing :: Indexing
Classifier: Topic :: Utilities
Classifier: Topic :: Internet
Classifier: Topic :: Software Development :: Libraries :: Python Modules
Classifier: Programming Language :: Python :: 3.5
